{"consumer_contract_version":"2.0","fragments":[{"field":"/conclusion","value":"個別企業を調べる対象はサイバーセキュリティ、地方銀行、運輸、バイオテクノロジー、石油・ガス開発です。回復条件を監視する対象はAI半導体、半導体製造装置です。長期材料はあるが、現在の株価は弱い対象は該当なしです。現在は避ける対象は住宅建設、インフラ建設、小売、AIソフトウェア・データ基盤、データセンター電力・インフラ、防衛、ネットワーク・光通信、原子力・ウランです。"},{"field":"/investment_meaning","value":"条件を満たす対象が少ない週は、件数を埋めず現金余力と調査時間を温存します。"},{"field":"/cautions/0","value":"政策や長期材料が良くても、現在の株価が弱い対象は自動的に昇格しません。"},{"field":"/next_checks/0","value":"回復条件を監視する対象が50日移動平均線と市場平均比を回復するか"}],"kind":"phase","meta":{"data_date":"2026-07-17","run_id":"c35c3efdd41f56306fd2c62b395b6b36f04a05a962f9868b5fdb216303862771","source_commit":"12bed664fa558a85a04ac7614d691e0a40813807","source_sha256":"c857d25094aee07bc6754a9f767dc0560225b6a8ab0d28cb2bdb66051729f1a9","status":"success"},"part":1,"part_count":1,"phase":4,"source_identity":{"analysis_id":"c35c3efdd41f56306fd2c62b395b6b36f04a05a962f9868b5fdb216303862771","generation_id":"ddf65f06cb01d0a83f5289227279ba34f61453384bfd70a66ae6a8c21d46b2e8"}}
